{
  "slides": [
    {
      "title": "Chair Slides",
      "url": "https://datatracker.ietf.org/meeting/126/materials/slides-126-ianabis-chair-slides-01"
    },
    {
      "title": "IANA IANABIS 126",
      "url": "https://datatracker.ietf.org/meeting/126/materials/slides-126-ianabis-iana-ianabis-126-02"
    },
    {
      "title": "Specification Required Sub-Policies",
      "url": "https://datatracker.ietf.org/meeting/126/materials/slides-126-ianabis-specification-required-sub-policies-00"
    }
  ],
  "bluesheetText": null,
  "polls": [],
  "chat": [
    {
      "author": "Harald Alvestrand",
      "text": "the squatting problem was why MIME media types had the \"standards tree\".",
      "time": "2026-07-20T09:38:13.000Z"
    },
    {
      "author": "Murray Kucherawy",
      "text": "Did we ever discuss anywhere what the definition of \"recognised\" should be?",
      "time": "2026-07-20T09:38:46.000Z"
    },
    {
      "author": "Eliot Lear",
      "text": "the iesg keeps a list",
      "time": "2026-07-20T09:39:10.000Z"
    },
    {
      "author": "Harald Alvestrand",
      "text": "Yes, extensively. That's the SDO registry.",
      "time": "2026-07-20T09:39:12.000Z"
    },
    {
      "author": "Murray Kucherawy",
      "text": "I know about that list, but there's no definition for what qualifies as \"recognised\".",
      "time": "2026-07-20T09:39:32.000Z"
    },
    {
      "author": "Murray Kucherawy",
      "text": "It's IESG judgement, and that can very as its membership changes.",
      "time": "2026-07-20T09:39:46.000Z"
    },
    {
      "author": "Harald Alvestrand",
      "text": "No, it's \"the IESG has decided that it's recognized\".",
      "time": "2026-07-20T09:39:47.000Z"
    },
    {
      "author": "Harald Alvestrand",
      "text": "so the IESG is responsible for documenting their policy.",
      "time": "2026-07-20T09:40:03.000Z"
    },
    {
      "author": "Murray Kucherawy",
      "text": "They never have though.",
      "time": "2026-07-20T09:40:14.000Z"
    },
    {
      "author": "Harald Alvestrand",
      "text": "which is not a new problem :-)",
      "time": "2026-07-20T09:40:29.000Z"
    },
    {
      "author": "Jonathan Lennox",
      "text": "Having this be semi-vibes-based by the IESG isn't terrible, it avoids making it gameable",
      "time": "2026-07-20T09:41:18.000Z"
    },
    {
      "author": "Murray Kucherawy",
      "text": "Interesting point.",
      "time": "2026-07-20T09:41:31.000Z"
    },
    {
      "author": "Martin Thomson",
      "text": "The slop problem is real, but I can't see this working.  Maybe we should stop making human-readable labels.",
      "time": "2026-07-20T09:42:32.000Z"
    },
    {
      "author": "Murray Kucherawy",
      "text": "That would solve the squatting problem.",
      "time": "2026-07-20T09:42:55.000Z"
    },
    {
      "author": "Murray Kucherawy",
      "text": "Queue closed; 8 queued, 46 minutes to go, one other presentation.",
      "time": "2026-07-20T09:44:11.000Z"
    },
    {
      "author": "Carsten Bormann",
      "text": "+1 Harald on underestimating reference permanence",
      "time": "2026-07-20T09:45:42.000Z"
    },
    {
      "author": "Martin Thomson",
      "text": "My mind is clearly not functioning well.  I filled in for Harald: \"when two implementations [love each other very much]...\"",
      "time": "2026-07-20T09:46:05.000Z"
    },
    {
      "author": "Ted Hardie",
      "text": "Remote folks, can you hear Amanda?",
      "time": "2026-07-20T09:55:06.000Z"
    },
    {
      "author": "Harald Alvestrand",
      "text": "I can hear her.",
      "time": "2026-07-20T09:55:15.000Z"
    },
    {
      "author": "Ted Hardie",
      "text": "Thanks @Harald",
      "time": "2026-07-20T09:55:22.000Z"
    },
    {
      "author": "Carsten Bormann",
      "text": "What is the implication for registering an SDO?  Does that imply permanence?  Or do we still need a separate consideration of that?",
      "time": "2026-07-20T09:58:18.000Z"
    },
    {
      "author": "Ted Hardie",
      "text": "Hi Carsten.  If the IESG removes them from the list, that would be effective for any requested actions after the removal.  Would you like that text in the document?",
      "time": "2026-07-20T09:59:14.000Z"
    },
    {
      "author": "Ted Hardie",
      "text": "You can't really say why people want choices--I remember someone asking the SRI-NIC for a specific IP prefix because it matched their telephone number prefix.",
      "time": "2026-07-20T10:03:11.000Z"
    },
    {
      "author": "Jonathan Lennox",
      "text": "Having the author not be allowed to suggest, say, the name of a new HTTP header field would be really weird.",
      "time": "2026-07-20T10:06:25.000Z"
    },
    {
      "author": "Carsten Bormann",
      "text": "Ted: I was thinking about reference permanence, which is somewhat independent of permanence of our recognition of the SDO.",
      "time": "2026-07-20T10:09:06.000Z"
    },
    {
      "author": "Rahul Gupta",
      "text": "Even numeric codes sometimes have a textual feel. Say HTTP 420 error code.",
      "time": "2026-07-20T10:09:41.000Z"
    },
    {
      "author": "Jonathan Lennox",
      "text": "Or 451.",
      "time": "2026-07-20T10:10:07.000Z"
    },
    {
      "author": "Harald Alvestrand",
      "text": "I think that in an ideal world, update procedures would be used much more than they presently are. Most permanent references are in reality pointing at obsolete documents.",
      "time": "2026-07-20T10:10:09.000Z"
    },
    {
      "author": "Murray Kucherawy",
      "text": "IMHO \"Yes\" on the 2119 question.",
      "time": "2026-07-20T10:11:09.000Z"
    },
    {
      "author": "Carsten Bormann",
      "text": "I'd rather have an obsolete document than no document",
      "time": "2026-07-20T10:13:12.000Z"
    },
    {
      "author": "Murray Kucherawy",
      "text": "As long as it makes its obsolesence plain.",
      "time": "2026-07-20T10:13:44.000Z"
    },
    {
      "author": "Carsten Bormann",
      "text": "Harald: I think we need to make more obvious how the \"change control\" power conferred to registrants is intended to be exercised",
      "time": "2026-07-20T10:13:59.000Z"
    },
    {
      "author": "John Klensin",
      "text": "Carsten +1",
      "time": "2026-07-20T10:14:54.000Z"
    },
    {
      "author": "Carsten Bormann",
      "text": "8126bis could open a registry of subpolicies, to be filled in by separate documents...",
      "time": "2026-07-20T10:16:44.000Z"
    },
    {
      "author": "Carsten Bormann",
      "text": "+1 no 2119 in IC sections (the section binds IANA and the registrant, not the implementer)",
      "time": "2026-07-20T10:17:46.000Z"
    },
    {
      "author": "Murray Kucherawy",
      "text": "That's exactly my reasoning too.",
      "time": "2026-07-20T10:17:57.000Z"
    },
    {
      "author": "Murray Kucherawy",
      "text": "If you want strong enforcement, assign a DE.",
      "time": "2026-07-20T10:18:12.000Z"
    },
    {
      "author": "Rahul Gupta",
      "text": "Can a registry designer not at extra rules for DE for that specific situation?",
      "time": "2026-07-20T10:18:51.000Z"
    },
    {
      "author": "Murray Kucherawy",
      "text": "Yes.",
      "time": "2026-07-20T10:18:58.000Z"
    },
    {
      "author": "Rahul Gupta",
      "text": "At =add*",
      "time": "2026-07-20T10:19:27.000Z"
    }
  ]
}