{
  "slides": [
    {
      "title": "00 Chair Slides",
      "url": "https://datatracker.ietf.org/meeting/126/materials/slides-126-anima-00-chair-slides-00"
    },
    {
      "title": "01 cBRSKI and Join Proxy",
      "url": "https://datatracker.ietf.org/meeting/126/materials/slides-126-anima-cbrski-and-join-proxy-00"
    },
    {
      "title": "03 The Constrained GRASP (cGRASP)",
      "url": "https://datatracker.ietf.org/meeting/126/materials/slides-126-anima-slide-126-anima-the-constrained-grasp-03-01"
    },
    {
      "title": "04 Autonomic Traffic Management in Artificial Intelligence Data Centers",
      "url": "https://datatracker.ietf.org/meeting/126/materials/slides-126-anima-autonomic-traffic-management-in-artificial-intelligence-data-centers-00"
    },
    {
      "title": "05 AI for Autonomic Networking and Agentic AI for Intent-Based Networking",
      "url": "https://datatracker.ietf.org/meeting/126/materials/slides-126-anima-ai-for-autonomic-networking-03"
    },
    {
      "title": "06 Problem Statement and Gap Analysis for Autonomic Networking with AI-ASA",
      "url": "https://datatracker.ietf.org/meeting/126/materials/slides-126-anima-06-problem-statement-and-gap-analysis-for-autonomic-networking-with-ai-asa-00"
    },
    {
      "title": "07 GRASP through routers: a Problem Statement",
      "url": "https://datatracker.ietf.org/meeting/126/materials/slides-126-anima-grasp-through-routers-a-problem-statement-01"
    },
    {
      "title": "08 Use Cases and Requirements for Network Admission of AI Agent Instances",
      "url": "https://datatracker.ietf.org/meeting/126/materials/slides-126-anima-use-cases-and-requirements-for-network-admission-of-ai-agent-instances-01"
    },
    {
      "title": "09 Campus Agent Identification and Scope-Down Access Control",
      "url": "https://datatracker.ietf.org/meeting/126/materials/slides-126-anima-campus-agent-identification-and-scope-down-access-control-02"
    }
  ],
  "bluesheetText": null,
  "polls": [],
  "chat": [
    {
      "author": "Michael Richardson",
      "text": "Hello from 126!",
      "time": "2026-07-21T14:30:51.000Z"
    },
    {
      "author": "Steffen Fries",
      "text": "Hi Toerless, regarding the status, BRSKI-PRM is in MISSREF, Mahesh pushed es forward.",
      "time": "2026-07-21T14:34:12.000Z"
    },
    {
      "author": "Mahesh Jethanandani",
      "text": "If I remember it correctly, the brski-prm draft was dependent on rfc8366bis. Since that document is now in IESG Evaluation state, it was a good time to let the brski-prm draft go into the RFC Editor queue.",
      "time": "2026-07-21T14:53:39.000Z"
    },
    {
      "author": "Steffen Fries",
      "text": "Yes true, thanks for pushing it forward.",
      "time": "2026-07-21T14:59:28.000Z"
    },
    {
      "author": "Toerless Eckert",
      "text": "Not sure if anyone else beside Steffen would need a say, sounds like a go ahead for Mahesh.",
      "time": "2026-07-21T15:00:36.000Z"
    },
    {
      "author": "Esko Dijk",
      "text": "GRASP through routers: we would go from zero-config to \"minimal-config - but not zero\" , it seems?",
      "time": "2026-07-21T15:46:29.000Z"
    },
    {
      "author": "Titouan Soulard",
      "text": "@Esko: totally right. One-per-subnet configuration is very minimal: relays know each other, but can be discovered by nodes. Omniscient configuration has more configuration: each node knows at least one relay.",
      "time": "2026-07-21T15:55:48.000Z"
    }
  ]
}