{
  "generated": "2026-03-13T18:18:38.477Z",
  "sessionGroups": [
    {
      "sessionName": "SCHC",
      "sessions": [
        {
          "sessionId": "IETF-SCHC-20230919-1400",
          "recordingUrl": "https://meetecho-player.ietf.org/playout/?session=IETF-SCHC-20230919-1400"
        }
      ]
    },
    {
      "sessionName": "TSVWG",
      "sessions": [
        {
          "sessionId": "IETF-TSVWG-20230919-1400",
          "recordingUrl": "https://meetecho-player.ietf.org/playout/?session=IETF-TSVWG-20230919-1400"
        }
      ]
    }
  ]
}