{
  "generated": "2026-03-12T22:54:44.621Z",
  "sessionGroups": [
    {
      "sessionName": "ASDF",
      "sessions": [
        {
          "sessionId": "IETF-ASDF-20260121-0700",
          "recordingUrl": "https://meetecho-player.ietf.org/playout/?session=IETF-ASDF-20260121-0700"
        }
      ]
    },
    {
      "sessionName": "CBOR",
      "sessions": [
        {
          "sessionId": "IETF-CBOR-20260121-1500",
          "recordingUrl": "https://meetecho-player.ietf.org/playout/?session=IETF-CBOR-20260121-1500"
        }
      ]
    }
  ]
}